LICENSE
MANIFEST.in
README.md
setup.py
wintersweet/__init__.py
wintersweet.egg-info/PKG-INFO
wintersweet.egg-info/SOURCES.txt
wintersweet.egg-info/dependency_links.txt
wintersweet.egg-info/requires.txt
wintersweet.egg-info/top_level.txt
wintersweet/asyncs/__init__.py
wintersweet/asyncs/cache/__init__.py
wintersweet/asyncs/http/__init__.py
wintersweet/asyncs/http/api.py
wintersweet/asyncs/http/default.py
wintersweet/asyncs/http/response.py
wintersweet/asyncs/http/utils.py
wintersweet/asyncs/ntp/__init__.py
wintersweet/asyncs/ntp/ntp_server.py
wintersweet/asyncs/pool/__init__.py
wintersweet/asyncs/pool/base.py
wintersweet/asyncs/pool/context.py
wintersweet/asyncs/pool/es.py
wintersweet/asyncs/pool/mongo.py
wintersweet/asyncs/pool/mysql.py
wintersweet/asyncs/pool/redis.py
wintersweet/asyncs/task/__init__.py
wintersweet/asyncs/task/interfaces.py
wintersweet/asyncs/task/tasks.py
wintersweet/asyncs/tools/__init__.py
wintersweet/asyncs/tools/circular.py
wintersweet/framework/__init__.py
wintersweet/framework/conf/__init__.py
wintersweet/framework/conf/global_setting.py
wintersweet/framework/fastapi/__init__.py
wintersweet/framework/fastapi/app.py
wintersweet/framework/fastapi/exception_handlers.py
wintersweet/framework/fastapi/middlewares.py
wintersweet/framework/fastapi/request.py
wintersweet/framework/fastapi/response.py
wintersweet/framework/fastapi/ws.py
wintersweet/utils/__init__.py
wintersweet/utils/base.py
wintersweet/utils/cache.py
wintersweet/utils/errors.py
wintersweet/utils/logging.py
wintersweet/utils/metaclass.py
wintersweet/utils/structure.py