Metadata-Version: 2.1
Name: wintersweet
Version: 1.1.0
Summary: Network Development Suite
Home-page: https://gitee.com/xixigroup/wintersweet
Author: Xixi.Dong
Author-email: xq1889@163.com
License: Apache License Version 2.0
Platform: all
Classifier: Programming Language :: Python :: 3.8
Classifier: License :: OSI Approved :: Apache Software License
Classifier: Operating System :: POSIX :: Linux
Requires-Python: >= 3.8
License-File: LICENSE
